my_site/manage.py
my_site-1.0.1.dist-info/LICENSE
my_site-1.0.1.dist-info/METADATA
my_site-1.0.1.dist-info/WHEEL
my_site-1.0.1.dist-info/entry_points.txt
my_site-1.0.1.dist-info/top_level.txt
my_site-1.0.1.dist-info/RECORD
