Metadata-Version: 2.1
Name: my-site
Version: 1.0.1
Summary: A Python package to make a poll.
Home-page: https://github.com
Author: Jesvin
Author-email: Jesvin@gmail.com
License: MIT
Platform: UNKNOWN
Classifier: License :: OSI Approved :: MIT License
Classifier: Programming Language :: Python :: 3
Classifier: Programming Language :: Python :: 3.7
Requires-Dist: sys
Requires-Dist: os
Requires-Dist: django
